e6data_python_connector/__init__.py
e6data_python_connector/cluster_manager.py
e6data_python_connector/common.py
e6data_python_connector/connection_pool.py
e6data_python_connector/constants.py
e6data_python_connector/datainputstream.py
e6data_python_connector/date_time_utils.py
e6data_python_connector/dialect.py
e6data_python_connector/e6data_grpc.py
e6data_python_connector/exceptions.py
e6data_python_connector/strategy.py
e6data_python_connector/typeId.py
e6data_python_connector/cluster_server/__init__.py
e6data_python_connector/cluster_server/cluster_pb2.py
e6data_python_connector/cluster_server/cluster_pb2_grpc.py
e6data_python_connector/e6x_vector/__init__.py
e6data_python_connector/e6x_vector/constants.py
e6data_python_connector/e6x_vector/ttypes.py
e6data_python_connector/server/QueryEngineService.py
e6data_python_connector/server/__init__.py
e6data_python_connector/server/constants.py
e6data_python_connector/server/e6x_engine_pb2.py
e6data_python_connector/server/e6x_engine_pb2.pyi
e6data_python_connector/server/e6x_engine_pb2_grpc.py
e6data_python_connector/server/ttypes.py
gen-py/__init__.py
gen-py/e6x_vector/__init__.py
gen-py/e6x_vector/constants.py
gen-py/e6x_vector/ttypes.py
test/__init__.py
test/analyze_38_nines.py
test/analyze_all_cases.py
test/analyze_binary.py
test/analyze_correct_value.py
test/analyze_fields.py
test/check_decimal_errors.py
test/cleanup_test_files.py
test/debug_38_nines.py
test/debug_binary.py
test/final_test.py
test/move_tests.py
test/quick_test.py
test/test_38_nines.py
test/test_all_decimal128_cases.py
test/test_cluster_manager_efficiency.py
test/test_cluster_manager_none_strategy.py
test/test_cluster_manager_strategy.py
test/test_comprehensive.py
test/test_connection_pool.py
test/test_connection_pool_e2e.py
test/test_current_implementation.py
test/test_decimal128_binary_parsing.py
test/test_decimal128_parsing.py
test/test_fix.py
test/test_improved_parsing.py
test/test_known_case.py
test/test_manual_analysis.py
e6data_python_connector-2.3.11.dist-info/LICENSE
e6data_python_connector-2.3.11.dist-info/METADATA
e6data_python_connector-2.3.11.dist-info/WHEEL
e6data_python_connector-2.3.11.dist-info/entry_points.txt
e6data_python_connector-2.3.11.dist-info/top_level.txt
e6data_python_connector-2.3.11.dist-info/RECORD
