Metadata-Version: 2.2
Name: e6data-python-connector
Version: 2.3.11
Summary: Client for the e6data distributed SQL Engine.
Home-page: https://github.com/e6x-labs/e6data-python-connector
Author: e6data, Inc.
Author-email: info@e6data.com
License: Apache 2.0
Classifier: Operating System :: POSIX :: Linux
Classifier: License :: OSI Approved :: Apache Software License
Classifier: Programming Language :: Python :: 3.5
Classifier: Programming Language :: Python :: 3.6
Classifier: Programming Language :: Python :: 3.7
Classifier: Programming Language :: Python :: 3.8
Classifier: Programming Language :: Python :: 3.9
Classifier: Programming Language :: Python :: 3.10
Classifier: Programming Language :: Python :: 3.11
Classifier: Programming Language :: Python :: 3.12
Classifier: Programming Language :: Python :: 3.13
License-File: LICENSE
Requires-Dist: sqlalchemy>=1.0.0
Requires-Dist: future>=1.0.0
Requires-Dist: python-dateutil>=2.9.0
Requires-Dist: pycryptodome>=3.19.1
Requires-Dist: pytz>=2024.1
Requires-Dist: thrift>=0.20.0
Requires-Dist: grpcio>=1.65.1
Requires-Dist: grpcio-tools>=1.65.1
Dynamic: author
Dynamic: author-email
Dynamic: classifier
Dynamic: description
Dynamic: description-content-type
Dynamic: home-page
Dynamic: license
Dynamic: requires-dist
Dynamic: summary
